pmlayer/__init__.py
pmlayer/common/__init__.py
pmlayer/common/util.py
pmlayer/torch/__init__.py
pmlayer/torch/hierarchical_lattice_layer.py
pmlayer/torch/linear_layer.py
pmlayer/torch/mlp.py
pmlayer/torch/piecewise_linear_layer.py
pmlayer/torch/layers/__init__.py
pmlayer-1.0.1.dist-info/LICENSE
pmlayer-1.0.1.dist-info/METADATA
pmlayer-1.0.1.dist-info/WHEEL
pmlayer-1.0.1.dist-info/top_level.txt
pmlayer-1.0.1.dist-info/RECORD
